fuzzy_secret_stdout/__init__.py
fuzzy_secret_stdout/__main__.py
fuzzy_secret_stdout/integrations/__init__.py
fuzzy_secret_stdout/integrations/aws_secret_manager.py
fuzzy_secret_stdout/integrations/aws_ssm.py
fuzzy_secret_stdout/integrations/factory.py
fuzzy_secret_stdout/models.py
fuzzy_secret_stdout-0.3.0.dist-info/LICENSE
fuzzy_secret_stdout-0.3.0.dist-info/METADATA
fuzzy_secret_stdout-0.3.0.dist-info/WHEEL
fuzzy_secret_stdout-0.3.0.dist-info/entry_points.txt
fuzzy_secret_stdout-0.3.0.dist-info/RECORD
