Metadata-Version: 2.1
Name: fuzzy-secret-stdout
Version: 0.3.0
Summary: Small utility to fuzzy search from a secret store and print the value to stdout
Home-page: https://pypi.org/project/fuzzy-secret-stdout/
License: MIT
Keywords: aws,secrets,ssm,parameter-store
Author: kiran94
Requires-Python: >=3.9,<4.0
Classifier: Intended Audience :: Developers
Classifier: License :: OSI Approved :: MIT License
Classifier: Operating System :: OS Independent
Classifier: Programming Language :: Python :: 3
Classifier: Programming Language :: Python :: 3.9
Classifier: Programming Language :: Python :: 3.10
Classifier: Programming Language :: Python :: 3.11
Classifier: Programming Language :: Python :: 3.12
Classifier: Topic :: Software Development
Classifier: Topic :: Utilities
Requires-Dist: boto3 (>=1.33.11,<2.0.0)
Requires-Dist: pyfzf (>=0.3.1,<0.4.0)
Requires-Dist: rich (>=13.7.0,<14.0.0)
Project-URL: Documentation, https://github.com/kiran94/fuzzy-secret-stdout/blob/main/README.md
Project-URL: Repository, https://github.com/kiran94/fuzzy-secret-stdout
